pytest_flake8_path/__init__.py
pytest_flake8_path/py.typed
pytest_flake8_path-1.7.0.dist-info/licenses/LICENSE
pytest_flake8_path-1.7.0.dist-info/METADATA
pytest_flake8_path-1.7.0.dist-info/WHEEL
pytest_flake8_path-1.7.0.dist-info/entry_points.txt
pytest_flake8_path-1.7.0.dist-info/top_level.txt
pytest_flake8_path-1.7.0.dist-info/RECORD
