Metadata-Version: 2.4
Name: pytest-flake8-path
Version: 1.7.0
Summary: A pytest fixture for testing flake8 plugins.
Author-email: Adam Johnson <me@adamj.eu>
License-Expression: MIT
Project-URL: Changelog, https://github.com/adamchainz/pytest-flake8-path/blob/main/CHANGELOG.rst
Project-URL: Funding, https://adamj.eu/books/
Project-URL: Repository, https://github.com/adamchainz/pytest-flake8-path
Keywords: flake8,pytest
Classifier: Development Status :: 5 - Production/Stable
Classifier: Framework :: Pytest
Classifier: Intended Audience :: Developers
Classifier: Natural Language :: English
Classifier: Operating System :: OS Independent
Classifier: Programming Language :: Python :: 3 :: Only
Classifier: Programming Language :: Python :: 3.9
Classifier: Programming Language :: Python :: 3.10
Classifier: Programming Language :: Python :: 3.11
Classifier: Programming Language :: Python :: 3.12
Classifier: Programming Language :: Python :: 3.13
Classifier: Programming Language :: Python :: 3.14
Classifier: Typing :: Typed
Requires-Python: >=3.9
License-File: LICENSE
Requires-Dist: flake8
Requires-Dist: pytest
Dynamic: license-file
